sardana_icepap/__init__.py
sardana_icepap/_version.py
sardana_icepap/ctrl/IcePAPCtrl.py
sardana_icepap/ctrl/IcePAPLinkedAxisController.py
sardana_icepap/ctrl/IcePAPPositionTriggerGateController.py
sardana_icepap/ctrl/IcePAPTriggerController.py
sardana_icepap/ctrl/__init__.py
sardana_icepap/ctrl/data/icepap.png
sardana_icepap/ctrl/data/icepaphw.png
sardana_icepap/ctrl/data/icepapicon.png
sardana_icepap/ctrl/test/__init__.py
sardana_icepap/ctrl/test/test_IcePAPPositionTriggerGateController.py
sardana_icepap/macro/__init__.py
sardana_icepap/macro/icepap_config.py
sardana_icepap/macro/icepap_esync.py
sardana_icepap/macro/icepap_homing.py
sardana_icepap/macro/icepap_resync.py
sardana_icepap/macro/icepap_utils.py
sardana_icepap-4.3.0.dist-info/licenses/LICENSE
sardana_icepap-4.3.0.dist-info/METADATA
sardana_icepap-4.3.0.dist-info/WHEEL
sardana_icepap-4.3.0.dist-info/top_level.txt
sardana_icepap-4.3.0.dist-info/RECORD
