Metadata-Version: 2.4
Name: sardana-icepap
Version: 4.3.0
Summary: IcePAP Sardana controller
License-Expression: GPL-3.0-or-later
Project-URL: Source, https://gitlab.com/icepap-organization/sardana-icepap
Requires-Python: >=3.9
License-File: LICENSE
Requires-Dist: sardana
Requires-Dist: icepap
Provides-Extra: tests
Requires-Dist: pytest; extra == "tests"
Dynamic: license-file
